./.gitignore
./.python-version
./PKG-INFO
./README.md
./pyproject.toml
./server.py
./uv.lock
mcp_dnsdumpster-0.1.3.dist-info/METADATA
mcp_dnsdumpster-0.1.3.dist-info/WHEEL
mcp_dnsdumpster-0.1.3.dist-info/entry_points.txt
mcp_dnsdumpster-0.1.3.dist-info/RECORD
