Metadata-Version: 2.4
Name: mcp-dnsdumpster
Version: 0.1.3
Summary: DNSDumpster MCP Server for querying DNS information
Project-URL: Homepage, https://github.com/MaxWeeden/mcp-dnsdumpster
Project-URL: Bug Tracker, https://github.com/MaxWeeden/mcp-dnsdumpster
Project-URL: Repository, https://github.com/MaxWeeden/mcp-dnsdumpster
Author-email: Max Weeden <mcp@greynova.xyz>
License-Expression: MIT
Keywords: claude,dns,dnsdumpster,mcp
Classifier: Development Status :: 3 - Alpha
Classifier: Intended Audience :: Developers
Classifier: License :: OSI Approved :: MIT License
Classifier: Programming Language :: Python :: 3
Classifier: Programming Language :: Python :: 3.10
Requires-Python: >=3.10
Requires-Dist: httpx>=0.28.1
Requires-Dist: mcp[cli]>=1.4.1
